LICENSE
MANIFEST.in
README.rst
setup.py
django_loaderio.egg-info/PKG-INFO
django_loaderio.egg-info/SOURCES.txt
django_loaderio.egg-info/dependency_links.txt
django_loaderio.egg-info/top_level.txt
loaderio/__init__.py
loaderio/admin.py
loaderio/models.py
loaderio/urls.py
loaderio/views.py
loaderio/migrations/0001_initial.py
loaderio/migrations/0002_auto__add_field_validation_enabled.py
loaderio/migrations/__init__.py