Metadata-Version: 1.1
Name: django-loaderio
Version: 0.3.0
Summary: An app for adding loader.io validation tokens
Home-page: https://github.com/sendgridlabs/loaderio-django
Author: Lorin Hochstein
Author-email: lorin.hochstein@sendgrid.com
License: MIT License
Platform: UNKNOWN
Classifier: Environment :: Web Environment
Classifier: Framework :: Django
Classifier: Intended Audience :: Developers
Classifier: License :: OSI Approved :: MIT License
Classifier: Operating System :: OS Independent
Classifier: Programming Language :: Python
Classifier: Programming Language :: Python :: 2
Classifier: Topic :: Internet :: WWW/HTTP
Classifier: Topic :: Internet :: WWW/HTTP :: Dynamic Content
